keras_models/__init__.py
keras_models/models/__init__.py
keras_models/models/cnn.py
keras_models/models/dnn.py
keras_models/models/linear.py
keras_models/models/resnet.py
keras_models/models/skip_gram.py
keras_models/models/text_cnn.py
keras_models/models/text_dnn.py
keras_models/models/wide_deep.py
keras_models/models/pretrained/__init__.py
keras_models/models/pretrained/vgg16_places365.py
keras_models/utils/__init__.py
keras_models/utils/nlp.py
keras_models-0.0.7.dist-info/LICENSE
keras_models-0.0.7.dist-info/METADATA
keras_models-0.0.7.dist-info/WHEEL
keras_models-0.0.7.dist-info/top_level.txt
keras_models-0.0.7.dist-info/RECORD
