Metadata-Version: 2.1
Name: keras-models
Version: 0.0.7
Summary: Keras Models Hub
Home-page: https://github.com/Marcnuth/Keras-Models
Author: Marcnuth
Author-email: hxianxian@gmail.com
License: Apache License 2.0
Platform: UNKNOWN
Classifier: Topic :: Scientific/Engineering :: Artificial Intelligence
Classifier: Topic :: Software Development :: Libraries
Classifier: Programming Language :: Python :: 3
